{"ad_search_list":null,"banner_dark":{"uri":"32e5200049fac86168117","url_list":["https://p3-sign.douyinpic.com/obj/32e5200049fac86168117?lk3s=03ea9982\u0026x-expires=1750140000\u0026x-signature=HbtA8Y0xhyI0Fk2WO63GLvBPACw%3D\u0026from=65706370","https://p26-sign.douyinpic.com/obj/32e5200049fac86168117?lk3s=03ea9982\u0026x-expires=1750140000\u0026x-signature=2MaNPPeARVJeen93Rs0%2BS4VU65k%3D\u0026from=65706370","https://p11-sign.douyinpic.com/obj/32e5200049fac86168117?lk3s=03ea9982\u0026x-expires=1750140000\u0026x-signature=TMvZHslCI%2FS4HfP64mPOue8iRsY%3D\u0026from=65706370"]},"banner_light":{"uri":"321f4000f703369c24604","url_list":["https://p26-sign.douyinpic.com/obj/321f4000f703369c24604?lk3s=03ea9982\u0026x-expires=1750140000\u0026x-signature=JB8Lmmd%2FDKS5TebWiOomEHao1wo%3D\u0026from=65706370","https://p3-sign.douyinpic.com/obj/321f4000f703369c24604?lk3s=03ea9982\u0026x-expires=1750140000\u0026x-signature=IqvOr5%2B%2BZ%2FCD4n1A1AZIh8tbn%2Fg%3D\u0026from=65706370","https://p11-sign.douyinpic.com/obj/321f4000f703369c24604?lk3s=03ea9982\u0026x-expires=1750140000\u0026x-signature=druMR5EAJeQKsRdOrz38TbeDTkE%3D\u0026from=65706370"]},"board_tabs":null,"data":{"active_time":"2025-06-17 08:56:48","recommend_list":null,"share_info":{"share_link_desc":"我在看抖音热榜，发现最火的内容，赶快来看！戳这里\u003e\u003e","share_title":"我在看抖音热榜，发现最火的内容，赶快来看！","share_url":"https://www.iesdouyin.com/share/billboard/?id=0"},"trending_desc":"实时上升热点","trending_list":[{"article_detail_count":0,"aweme_infos":null,"discuss_video_count":1,"display_style":0,"drift_info":null,"event_time":1750051631,"group_id":"7514352380101989683","hot_value":0,"hotlist_param":"{\"version\":1}","label":0,"related_words":null,"sentence_id":"2133017","sentence_tag":3001,"video_count":3,"word":"我国实现钇举突破","word_cover":{"uri":"tos-cn-p-0015/oUTA5ElDg1DBtyZFfgo9ACArITOeNTITktHFrC","url_list":["https://p3-sign.douyinpic.com/tos-cn-p-0015/oUTA5ElDg1DBtyZFfgo9ACArITOeNTITktHFrC~noop.jpeg?lk3s=bfd515bb\u0026x-expires=1750140000\u0026x-signature=tLvX%2FCf1HSLLsmEt%2FRc4aCeUFK4%3D\u0026from=3218412987","https://p26-sign.douyinpic.com/tos-cn-p-0015/oUTA5ElDg1DBtyZFfgo9ACArITOeNTITktHFrC~noop.jpeg?lk3s=bfd515bb\u0026x-expires=1750140000\u0026x-signature=txFSJy38nP9D1FlyyIya6HnWHZY%3D\u0026from=3218412987","https://p11-sign.douyinpic.com/tos-cn-p-0015/oUTA5ElDg1DBtyZFfgo9ACArITOeNTITktHFrC~noop.jpeg?lk3s=bfd515bb\u0026x-expires=1750140000\u0026x-signature=zktXwPnrLRpWO87J9ZsyDVmJQ%2Bg%3D\u0026from=3218412987"]},"word_sub_board":null,"word_type":3},{"article_detail_count":0,"aweme_infos":null,"discuss_video_count":1,"display_style":0,"drift_info":null,"event_time":1750067815,"group_id":"7514911689167639845","hot_value":0,"hotlist_param":"{\"version\":1}","label":0,"related_words":null,"sentence_id":"2133466","sentence_tag":1002,"video_count":10,"word":"来战张震岳的小宇翻唱","word_cover":{"uri":"tos-cn-p-0015/o8lB27P1IEP3TPXZUIaiAOBQFdi0wQEI6wxAD","url_list":["https://p3-sign.douyinpic.com/tos-cn-p-0015/o8lB27P1IEP3TPXZUIaiAOBQFdi0wQEI6wxAD~noop.jpeg?lk3s=bfd515bb\u0026x-expires=1750140000\u0026x-signature=joaVRnWa8sIJrTw7sppxNT%2FCuck%3D\u0026from=3218412987","https://p11-sign.douyinpic.com/tos-cn-p-0015/o8lB27P1IEP3TPXZUIaiAOBQFdi0wQEI6wxAD~noop.jpeg?lk3s=bfd515bb\u0026x-expires=1750140000\u0026x-signature=kOEpxu%2FPCzQ3UsoZEoIli2TXlaI%3D\u0026from=3218412987","https://p26-sign.douyinpic.com/tos-cn-p-0015/o8lB27P1IEP3TPXZUIaiAOBQFdi0wQEI6wxAD~noop.jpeg?lk3s=bfd515bb\u0026x-expires=1750140000\u0026x-signature=%2BASmoMLEsIHfH4eYV1w2UhH8A2o%3D\u0026from=3218412987"]},"word_sub_board":[3],"word_type":3},{"aweme_infos":null,"discuss_video_count":1,"display_style":0,"drift_info":null,"event_time":1750069859,"group_id":"7514995983681312026","hot_value":0,"hotlist_param":"{\"version\":1}","label":0,"related_words":null,"sentence_id":"2133556","sentence_tag":2002,"video_count":1,"word":"七根心简有自己的扫地僧","word_cover":{"uri":"tos-cn-p-0015/ogofuoR1fAB1D5DpAbOPmOIgcF9s7ToUtCEIAM","url_list":["https://p3-sign.douyinpic.com/tos-cn-p-0015/ogofuoR1fAB1D5DpAbOPmOIgcF9s7ToUtCEIAM~noop.jpeg?lk3s=bfd515bb\u0026x-expires=1750140000\u0026x-signature=xZL81z694HFlBw62%2B8HRHnRwHBE%3D\u0026from=3218412987","https://p26-sign.douyinpic.com/tos-cn-p-0015/ogofuoR1fAB1D5DpAbOPmOIgcF9s7ToUtCEIAM~noop.jpeg?lk3s=bfd515bb\u0026x-expires=1750140000\u0026x-signature=hv%2BXyjx%2BHau1kwiDhFtZ8MlekZk%3D\u0026from=3218412987","https://p11-sign.douyinpic.com/tos-cn-p-0015/ogofuoR1fAB1D5DpAbOPmOIgcF9s7ToUtCEIAM~noop.jpeg?lk3s=bfd515bb\u0026x-expires=1750140000\u0026x-signature=QMhtjBk1RN4XussuxEDE6K3XHsk%3D\u0026from=3218412987"]},"word_sub_board":null,"word_type":3},{"article_detail_count":0,"aweme_infos":null,"discuss_video_count":1,"display_style":0,"drift_info":null,"event_time":1750071123,"group_id":"7515051039082206515","hot_value":0,"hotlist_param":"{\"version\":1}","label":0,"related_words":null,"sentence_id":"2133515","sentence_tag":1003,"video_count":7,"word":"人设属性一键扫描","word_cover":{"uri":"tos-cn-p-0015c000-ce/oYI7ZfQbYK9lUCGfCgeaLXA8CWIldATlJymQJB","url_list":["https://p3-sign.douyinpic.com/tos-cn-p-0015c000-ce/oYI7ZfQbYK9lUCGfCgeaLXA8CWIldATlJymQJB~noop.jpeg?lk3s=bfd515bb\u0026x-expires=1750140000\u0026x-signature=oYyRxGalvIO12QToaj5l6NjUjM4%3D\u0026from=3218412987","https://p26-sign.douyinpic.com/tos-cn-p-0015c000-ce/oYI7ZfQbYK9lUCGfCgeaLXA8CWIldATlJymQJB~noop.jpeg?lk3s=bfd515bb\u0026x-expires=1750140000\u0026x-signature=Km7%2BhYh%2BPj%2B22TQqefQYaVJSpFk%3D\u0026from=3218412987","https://p9-sign.douyinpic.com/tos-cn-p-0015c000-ce/oYI7ZfQbYK9lUCGfCgeaLXA8CWIldATlJymQJB~noop.jpeg?lk3s=bfd515bb\u0026x-expires=1750140000\u0026x-signature=gw3Tzo3J9ghRxrwn%2FzyrvdAacnk%3D\u0026from=3218412987"]},"word_sub_board":[3],"word_type":3},{"article_detail_count":0,"aweme_infos":null,"discuss_video_count":1,"display_style":0,"drift_info":null,"event_time":1749773627,"group_id":"6709294269384889613","hot_value":0,"hotlist_param":"{\"version\":1}","label":0,"related_words":null,"room_count":0,"sentence_id":"2128892","sentence_tag":21000,"video_count":10,"word":"以色列对伊朗发动袭击","word_cover":{"uri":"tos-cn-p-0015/oMfQRx7BBnDlqL8ENbF5eIi0BEiAIACftMCGPA","url_list":["https://p26-sign.douyinpic.com/tos-cn-p-0015/oMfQRx7BBnDlqL8ENbF5eIi0BEiAIACftMCGPA~noop.jpeg?lk3s=bfd515bb\u0026x-expires=1750140000\u0026x-signature=TCqELqqqn0brZqwFxLtLSPUGU2g%3D\u0026from=3218412987","https://p3-sign.douyinpic.com/tos-cn-p-0015/oMfQRx7BBnDlqL8ENbF5eIi0BEiAIACftMCGPA~noop.jpeg?lk3s=bfd515bb\u0026x-expires=1750140000\u0026x-signature=RNGPGLT0Y0h5VZEp4qi%2BPBBw4gY%3D\u0026from=3218412987","https://p11-sign.douyinpic.com/tos-cn-p-0015/oMfQRx7BBnDlqL8ENbF5eIi0BEiAIACftMCGPA~noop.jpeg?lk3s=bfd515bb\u0026x-expires=1750140000\u0026x-signature=zBExgmc4dbc60ShG%2B%2FWZNhYZhSg%3D\u0026from=3218412987"]},"word_sub_board":null,"word_type":3}],"word_list":[{"article_detail_count":0,"aweme_infos":null,"can_extend_detail":false,"discuss_video_count":1,"display_style":0,"drift_info":null,"event_time":1750115958,"group_id":"7418978166498907429","hot_value":11949271,"hotlist_param":"{\"version\":1}","label":1,"position":1,"related_words":null,"sentence_id":"2133811","sentence_tag":3002,"video_count":3,"view_count":69125993,"word":"中东有全面开战的可能吗","word_cover":{"uri":"tos-cn-p-0015/oQMEcAfizgK20RUCTIBmerAXCuIOiXANB55BMQ","url_list":["https://p3-sign.douyinpic.com/tos-cn-p-0015/oQMEcAfizgK20RUCTIBmerAXCuIOiXANB55BMQ~noop.jpeg?lk3s=bfd515bb\u0026x-expires=1750140000\u0026x-signature=y0nbJ5hYaAUnE0k7zGFlSRW%2BKM4%3D\u0026from=3218412987","https://p11-sign.douyinpic.com/tos-cn-p-0015/oQMEcAfizgK20RUCTIBmerAXCuIOiXANB55BMQ~noop.jpeg?lk3s=bfd515bb\u0026x-expires=1750140000\u0026x-signature=pOW9Xx5GE63Q%2F3fAKaEAlbO1OD0%3D\u0026from=3218412987","https://p26-sign.douyinpic.com/tos-cn-p-0015/oQMEcAfizgK20RUCTIBmerAXCuIOiXANB55BMQ~noop.jpeg?lk3s=bfd515bb\u0026x-expires=1750140000\u0026x-signature=prxiVDM0WY0Okt48uxktnA4VeSs%3D\u0026from=3218412987"]},"word_sub_board":null,"word_type":1},{"article_detail_count":0,"aweme_infos":null,"can_extend_detail":false,"discuss_video_count":1,"display_style":0,"drift_info":null,"event_time":1750117180,"group_id":"7515069223342642441","hot_value":11882680,"hotlist_param":"{\"version\":1}","label":1,"position":2,"related_words":null,"sentence_id":"2133851","sentence_tag":5000,"video_count":3,"view_count":59922354,"word":"中足联呼吁：坚决抵制不当行为","word_cover":{"uri":"tos-cn-p-0015/o0FKDEuIBOsJBBJHgifOA1BHgiQlV0AAJ0Be6Q","url_list":["https://p3-sign.douyinpic.com/tos-cn-p-0015/o0FKDEuIBOsJBBJHgifOA1BHgiQlV0AAJ0Be6Q~noop.jpeg?lk3s=bfd515bb\u0026x-expires=1750140000\u0026x-signature=zCC4g0cXr2A%2FYtcwQh5ZkilM1x8%3D\u0026from=3218412987","https://p26-sign.douyinpic.com/tos-cn-p-0015/o0FKDEuIBOsJBBJHgifOA1BHgiQlV0AAJ0Be6Q~noop.jpeg?lk3s=bfd515bb\u0026x-expires=1750140000\u0026x-signature=qv40Pc%2Bj2aR8jUh1Mq1551nPWTw%3D\u0026from=3218412987","https://p11-sign.douyinpic.com/tos-cn-p-0015/o0FKDEuIBOsJBBJHgifOA1BHgiQlV0AAJ0Be6Q~noop.jpeg?lk3s=bfd515bb\u0026x-expires=1750140000\u0026x-signature=eqU9CEJrsBvhyq3phzgi2yhrQqY%3D\u0026from=3218412987"]},"word_sub_board":null,"word_type":1},{"article_detail_count":0,"aweme_infos":null,"can_extend_detail":false,"discuss_video_count":1,"display_style":0,"drift_info":null,"event_time":1750083049,"group_id":"6976221911026455815","hot_value":11787638,"hotlist_param":"{\"version\":1}","label":3,"position":3,"related_words":null,"sentence_id":"2133739","sentence_tag":3001,"video_count":3,"view_count":57517088,"word":"5月份国民经济运行总体平稳","word_cover":{"uri":"tos-cn-p-0015/oED3PJfSAMo6oFeAh27BAODKETQApI8g9qxbFN","url_list":["https://p3-sign.douyinpic.com/tos-cn-p-0015/oED3PJfSAMo6oFeAh27BAODKETQApI8g9qxbFN~noop.jpeg?lk3s=bfd515bb\u0026x-expires=1750140000\u0026x-signature=B2HReR4KXwBar1vvMklsFmiWuBk%3D\u0026from=3218412987","https://p11-sign.douyinpic.com/tos-cn-p-0015/oED3PJfSAMo6oFeAh27BAODKETQApI8g9qxbFN~noop.jpeg?lk3s=bfd515bb\u0026x-expires=1750140000\u0026x-signature=6Ce1UgaknvsWknQcbF8XF%2BZpavM%3D\u0026from=3218412987","https://p26-sign.douyinpic.com/tos-cn-p-0015/oED3PJfSAMo6oFeAh27BAODKETQApI8g9qxbFN~noop.jpeg?lk3s=bfd515bb\u0026x-expires=1750140000\u0026x-signature=flNr9zq8H%2BrrcaGl%2Fd4N1tGULrI%3D\u0026from=3218412987"]},"word_sub_board":null,"word_type":1},{"article_detail_count":0,"aweme_infos":null,"can_extend_detail":false,"discuss_video_count":1,"display_style":0,"drift_info":null,"event_time":1750055604,"group_id":"7514951997247231258","hot_value":11695600,"hotlist_param":"{\"version\":1}","label":3,"position":4,"related_words":null,"sentence_id":"2133127","sentence_tag":7000,"video_count":3,"view_count":64261523,"word":"青年人失业率连续3个月下降","word_cover":{"uri":"tos-cn-p-0015/o49qPAcUeCJhxiI0ZJivABgrqmAVa0I9eGB3An","url_list":["https://p3-sign.douyinpic.com/tos-cn-p-0015/o49qPAcUeCJhxiI0ZJivABgrqmAVa0I9eGB3An~noop.jpeg?lk3s=bfd515bb\u0026x-expires=1750140000\u0026x-signature=gXwPxXCPdriWWdtu0%2FE8vqQXR28%3D\u0026from=3218412987","https://p26-sign.douyinpic.com/tos-cn-p-0015/o49qPAcUeCJhxiI0ZJivABgrqmAVa0I9eGB3An~noop.jpeg?lk3s=bfd515bb\u0026x-expires=1750140000\u0026x-signature=P4GH8eyPMCT69RqBPidTUfdU5go%3D\u0026from=3218412987","https://p11-sign.douyinpic.com/tos-cn-p-0015/o49qPAcUeCJhxiI0ZJivABgrqmAVa0I9eGB3An~noop.jpeg?lk3s=bfd515bb\u0026x-expires=1750140000\u0026x-signature=%2BNTbbsd8VH6CQSTkcLlgU%2BjCsdc%3D\u0026from=3218412987"]},"word_sub_board":null,"word_type":1},{"article_detail_count":0,"aweme_infos":null,"can_extend_detail":false,"discuss_video_count":1,"display_style":0,"drift_info":null,"event_time":1750051426,"group_id":"6742153847398995203","hot_value":10848826,"hotlist_param":"{\"version\":1}","label":0,"position":5,"related_words":null,"sentence_id":"2133003","sentence_tag":7000,"video_count":3,"view_count":55757441,"word":"油价将迎来年内第五次上调","word_cover":{"uri":"tos-cn-p-0015/oUaLvA2T6IIE5BQ7pViJTipEIP0oAkjwvW3xN","url_list":["https://p9-sign.douyinpic.com/tos-cn-p-0015/oUaLvA2T6IIE5BQ7pViJTipEIP0oAkjwvW3xN~noop.jpeg?lk3s=bfd515bb\u0026x-expires=1750140000\u0026x-signature=odnoLXHDYdF6d4P1nJjaZUNfOZo%3D\u0026from=3218412987","https://p3-sign.douyinpic.com/tos-cn-p-0015/oUaLvA2T6IIE5BQ7pViJTipEIP0oAkjwvW3xN~noop.jpeg?lk3s=bfd515bb\u0026x-expires=1750140000\u0026x-signature=Ct8j6%2FrXp7XMYzYSCjbPN9LaEaI%3D\u0026from=3218412987","https://p26-sign.douyinpic.com/tos-cn-p-0015/oUaLvA2T6IIE5BQ7pViJTipEIP0oAkjwvW3xN~noop.jpeg?lk3s=bfd515bb\u0026x-expires=1750140000\u0026x-signature=Z16S3VnmRL%2BXnjC%2FU282aKbFwC0%3D\u0026from=3218412987"]},"word_sub_board":null,"word_type":1},{"article_detail_count":0,"aweme_infos":null,"can_extend_detail":false,"discuss_video_count":1,"display_style":0,"drift_info":null,"event_time":1750118846,"group_id":"7507863383724578098","hot_value":10676323,"hotlist_param":"{\"version\":1}","label":1,"position":6,"related_words":null,"sentence_id":"2133893","sentence_tag":5000,"video_count":2,"view_count":56389526,"word":"步行者vs雷霆G5","word_cover":{"uri":"tos-cn-p-0015/ocfBGI0GAUzCYzgLeKQ7BHArQSexnngdvXh0jE","url_list":["https://p3-sign.douyinpic.com/tos-cn-p-0015/ocfBGI0GAUzCYzgLeKQ7BHArQSexnngdvXh0jE~noop.jpeg?lk3s=bfd515bb\u0026x-expires=1750140000\u0026x-signature=EOZjn9MnUTRVEsEWXJBiiISn5QU%3D\u0026from=3218412987","https://p11-sign.douyinpic.com/tos-cn-p-0015/ocfBGI0GAUzCYzgLeKQ7BHArQSexnngdvXh0jE~noop.jpeg?lk3s=bfd515bb\u0026x-expires=1750140000\u0026x-signature=P4GYRkPLd9sIgs2Y36YcDxiiFjY%3D\u0026from=3218412987","https://p26-sign.douyinpic.com/tos-cn-p-0015/ocfBGI0GAUzCYzgLeKQ7BHArQSexnngdvXh0jE~noop.jpeg?lk3s=bfd515bb\u0026x-expires=1750140000\u0026x-signature=XCetT6H73V3PFaLTx%2FehoJwa0Ds%3D\u0026from=3218412987"]},"word_sub_board":null,"word_type":1},{"article_detail_count":0,"aweme_infos":null,"can_extend_detail":false,"discuss_video_count":1,"display_style":0,"drift_info":null,"event_time":1750040091,"group_id":"7513838237368243508","hot_value":9437906,"hotlist_param":"{\"version\":1}","label":0,"position":7,"related_words":null,"sentence_id":"2132701","sentence_tag":3002,"video_count":1,"view_count":52726418,"word":"伊以双方伤亡情况","word_cover":{"uri":"tos-cn-p-0015/o8Geka01gCtndgIpxe7eB4qB6YbgvANuIkACLQ","url_list":["https://p3-sign.douyinpic.com/tos-cn-p-0015/o8Geka01gCtndgIpxe7eB4qB6YbgvANuIkACLQ~noop.jpeg?lk3s=bfd515bb\u0026x-expires=1750140000\u0026x-signature=44YBzSXpe%2FgzlJaPyooS%2FmARBpE%3D\u0026from=3218412987","https://p26-sign.douyinpic.com/tos-cn-p-0015/o8Geka01gCtndgIpxe7eB4qB6YbgvANuIkACLQ~noop.jpeg?lk3s=bfd515bb\u0026x-expires=1750140000\u0026x-signature=lC0QpYYfD34xKangcllPlNb0%2BuY%3D\u0026from=3218412987","https://p11-sign.douyinpic.com/tos-cn-p-0015/o8Geka01gCtndgIpxe7eB4qB6YbgvANuIkACLQ~noop.jpeg?lk3s=bfd515bb\u0026x-expires=1750140000\u0026x-signature=YIr3ZC4nrZDN7Q1mWAcyYziO2Io%3D\u0026from=3218412987"]},"word_sub_board":null,"word_type":1},{"article_detail_count":0,"aweme_infos":null,"can_extend_detail":false,"discuss_video_count":1,"display_style":0,"drift_info":null,"event_time":1750117366,"group_id":"7515038923954099494","hot_value":9415531,"hotlist_param":"{\"version\":1}","label":1,"position":8,"related_words":null,"sentence_id":"2133862","sentence_tag":3002,"video_count":2,"view_count":50990992,"word":"21国联合声明谴责以色列","word_cover":{"uri":"tos-cn-p-0015/oMIAQFoIKBlPA5DVIfyLRNBgEOpeaU089BVA9Y","url_list":["https://p3-sign.douyinpic.com/tos-cn-p-0015/oMIAQFoIKBlPA5DVIfyLRNBgEOpeaU089BVA9Y~noop.jpeg?lk3s=bfd515bb\u0026x-expires=1750140000\u0026x-signature=KVe9iSoSjaycJnl3RN9BGSs42lY%3D\u0026from=3218412987","https://p26-sign.douyinpic.com/tos-cn-p-0015/oMIAQFoIKBlPA5DVIfyLRNBgEOpeaU089BVA9Y~noop.jpeg?lk3s=bfd515bb\u0026x-expires=1750140000\u0026x-signature=ZInaBi1NQ58VdSOZ6bTJbLO2R3g%3D\u0026from=3218412987","https://p9-sign.douyinpic.com/tos-cn-p-0015/oMIAQFoIKBlPA5DVIfyLRNBgEOpeaU089BVA9Y~noop.jpeg?lk3s=bfd515bb\u0026x-expires=1750140000\u0026x-signature=Aqikf8L%2BRDrNDs6DC5o%2FRBCDXpE%3D\u0026from=3218412987"]},"word_sub_board":null,"word_type":1},{"article_detail_count":0,"aweme_infos":null,"can_extend_detail":false,"discuss_video_count":1,"display_style":0,"drift_info":null,"event_time":1750083097,"group_id":"7106391569323316520","hot_value":9300777,"hotlist_param":"{\"version\":1}","label":3,"position":9,"related_words":null,"sentence_id":"2133740","sentence_tag":3001,"video_count":2,"view_count":51667407,"word":"高考志愿填报要做哪些准备","word_cover":{"uri":"tos-cn-p-0015/oU74pCCDoBzhSSeFEVy8bAIrAAyPfTSgq9IkF9","url_list":["https://p26-sign.douyinpic.com/tos-cn-p-0015/oU74pCCDoBzhSSeFEVy8bAIrAAyPfTSgq9IkF9~noop.jpeg?lk3s=bfd515bb\u0026x-expires=1750140000\u0026x-signature=UHvCO%2FMWVYR9BqM3eTPy3%2FyJ1cc%3D\u0026from=3218412987","https://p3-sign.douyinpic.com/tos-cn-p-0015/oU74pCCDoBzhSSeFEVy8bAIrAAyPfTSgq9IkF9~noop.jpeg?lk3s=bfd515bb\u0026x-expires=1750140000\u0026x-signature=6hDjNozwG1bJ3Kh8RBHF0G5VP5k%3D\u0026from=3218412987","https://p11-sign.douyinpic.com/tos-cn-p-0015/oU74pCCDoBzhSSeFEVy8bAIrAAyPfTSgq9IkF9~noop.jpeg?lk3s=bfd515bb\u0026x-expires=1750140000\u0026x-signature=P2B5i5AQFLbzNueGmlnY%2BLV6y2U%3D\u0026from=3218412987"]},"word_sub_board":null,"word_type":1},{"article_detail_count":0,"aweme_infos":null,"can_extend_detail":false,"discuss_video_count":1,"display_style":0,"drift_info":null,"event_time":1750061169,"group_id":"7006515851034531083","hot_value":9281192,"hotlist_param":"{\"version\":1}","label":0,"position":10,"related_words":null,"sentence_id":"2133283","sentence_tag":20002,"video_count":8,"view_count":48530626,"word":"期末周怎么过","word_cover":{"uri":"tos-cn-i-dy/977c9e46745b4971b84e862b5a2e4bbf","url_list":["https://p3-sign.douyinpic.com/tos-cn-i-dy/977c9e46745b4971b84e862b5a2e4bbf~noop.jpeg?lk3s=bfd515bb\u0026x-expires=1750140000\u0026x-signature=PpzOua8XMHVBj4F7L%2Fdl69loVA0%3D\u0026from=3218412987","https://p26-sign.douyinpic.com/tos-cn-i-dy/977c9e46745b4971b84e862b5a2e4bbf~noop.jpeg?lk3s=bfd515bb\u0026x-expires=1750140000\u0026x-signature=zCnkBdUOnetz42G8fEBybNThmgM%3D\u0026from=3218412987","https://p9-sign.douyinpic.com/tos-cn-i-dy/977c9e46745b4971b84e862b5a2e4bbf~noop.jpeg?lk3s=bfd515bb\u0026x-expires=1750140000\u0026x-signature=elhnmOLw%2FXbMjNI98dhNGEnBDW8%3D\u0026from=3218412987"]},"word_sub_board":null,"word_type":1},{"article_detail_count":0,"aweme_infos":null,"can_extend_detail":false,"discuss_video_count":1,"display_style":0,"drift_info":null,"event_time":1750039368,"group_id":"7216868051194320131","hot_value":9236299,"hotlist_param":"{\"version\":1}","label":0,"position":11,"related_words":null,"sentence_id":"2132676","sentence_tag":20002,"video_count":3,"view_count":49930090,"word":"雨再大也浇不灭跳舞的灵魂","word_cover":{"uri":"tos-cn-p-0015/ocehW6dEvQ3sgAIUeD6LnBTGC7jYng7eOwEAOB","url_list":["https://p26-sign.douyinpic.com/tos-cn-p-0015/ocehW6dEvQ3sgAIUeD6LnBTGC7jYng7eOwEAOB~noop.jpeg?lk3s=bfd515bb\u0026x-expires=1750140000\u0026x-signature=JrZ6wo16OWr9lXejyJmPT8AC5g4%3D\u0026from=3218412987","https://p11-sign.douyinpic.com/tos-cn-p-0015/ocehW6dEvQ3sgAIUeD6LnBTGC7jYng7eOwEAOB~noop.jpeg?lk3s=bfd515bb\u0026x-expires=1750140000\u0026x-signature=XYZSgn8Kn2jcKGJB5nSDHyA208w%3D\u0026from=3218412987","https://p3-sign.douyinpic.com/tos-cn-p-0015/ocehW6dEvQ3sgAIUeD6LnBTGC7jYng7eOwEAOB~noop.jpeg?lk3s=bfd515bb\u0026x-expires=1750140000\u0026x-signature=AyVzb5z9nzcvY1McnCTOZ0oAqOs%3D\u0026from=3218412987"]},"word_sub_board":null,"word_type":1},{"article_detail_count":0,"aweme_infos":null,"can_extend_detail":false,"discuss_video_count":1,"display_style":0,"drift_info":null,"event_time":1750050695,"group_id":"7514943972122465587","hot_value":9215344,"hotlist_param":"{\"version\":1}","label":0,"position":12,"related_words":null,"sentence_id":"2132976","sentence_tag":7000,"video_count":3,"view_count":48090209,"word":"伊以冲突升级震动全球市场","word_cover":{"uri":"tos-cn-p-0015/o8Be9VEQQAgowkTfBhFNPap34DQaFAAWDB49Em","url_list":["https://p3-sign.douyinpic.com/tos-cn-p-0015/o8Be9VEQQAgowkTfBhFNPap34DQaFAAWDB49Em~noop.jpeg?lk3s=bfd515bb\u0026x-expires=1750140000\u0026x-signature=tI%2FEN73%2BFf8c9egqtpxiCYQXhU0%3D\u0026from=3218412987","https://p26-sign.douyinpic.com/tos-cn-p-0015/o8Be9VEQQAgowkTfBhFNPap34DQaFAAWDB49Em~noop.jpeg?lk3s=bfd515bb\u0026x-expires=1750140000\u0026x-signature=Y%2BycIL4Md30IpM4xMijnbynEAOY%3D\u0026from=3218412987","https://p11-sign.douyinpic.com/tos-cn-p-0015/o8Be9VEQQAgowkTfBhFNPap34DQaFAAWDB49Em~noop.jpeg?lk3s=bfd515bb\u0026x-expires=1750140000\u0026x-signature=GPU8AcNX5knnLJOLV6ocrYDFiKE%3D\u0026from=3218412987"]},"word_sub_board":null,"word_type":1},{"article_detail_count":0,"aweme_infos":null,"can_extend_detail":false,"discuss_video_count":1,"display_style":0,"drift_info":null,"event_time":1750073881,"group_id":"7514989952293541146","hot_value":9155977,"hotlist_param":"{\"version\":1}","label":0,"position":13,"related_words":null,"sentence_id":"2133592","sentence_tag":2003,"video_count":1,"view_count":52289480,"word":"管乐承认自己是恋爱脑","word_cover":{"uri":"tos-cn-p-0015/og7KPofYEgLlAFEViECIbgAVn8xSBWDiAIAf91","url_list":["https://p3-sign.douyinpic.com/tos-cn-p-0015/og7KPofYEgLlAFEViECIbgAVn8xSBWDiAIAf91~noop.jpeg?lk3s=bfd515bb\u0026x-expires=1750140000\u0026x-signature=qeDOrxpkNhNaH%2B%2FOzQXUh%2Bx5n1k%3D\u0026from=3218412987","https://p9-sign.douyinpic.com/tos-cn-p-0015/og7KPofYEgLlAFEViECIbgAVn8xSBWDiAIAf91~noop.jpeg?lk3s=bfd515bb\u0026x-expires=1750140000\u0026x-signature=57vTZwBmzwc93eGCGVj6tD7hqWU%3D\u0026from=3218412987","https://p26-sign.douyinpic.com/tos-cn-p-0015/og7KPofYEgLlAFEViECIbgAVn8xSBWDiAIAf91~noop.jpeg?lk3s=bfd515bb\u0026x-expires=1750140000\u0026x-signature=s0RiFJGnpxHk%2BpYxrQ8oyj0iSNY%3D\u0026from=3218412987"]},"word_sub_board":null,"word_type":1},{"article_detail_count":0,"aweme_infos":null,"can_extend_detail":false,"discuss_video_count":1,"display_style":0,"drift_info":null,"event_time":1750060821,"group_id":"6973664933561832716","hot_value":9111750,"hotlist_param":"{\"version\":1}","label":0,"position":14,"related_words":null,"sentence_id":"2133270","sentence_tag":20002,"video_count":1,"view_count":46665552,"word":"他俩最后谁晋级了","word_cover":{"uri":"tos-cn-p-0015/oANJBvzVAi9CIWztIC0giBnPELefANSQtADITE","url_list":["https://p26-sign.douyinpic.com/tos-cn-p-0015/oANJBvzVAi9CIWztIC0giBnPELefANSQtADITE~noop.jpeg?lk3s=bfd515bb\u0026x-expires=1750140000\u0026x-signature=NnOlUzyvZVV6hl9TtXPZ7oJOWtA%3D\u0026from=3218412987","https://p3-sign.douyinpic.com/tos-cn-p-0015/oANJBvzVAi9CIWztIC0giBnPELefANSQtADITE~noop.jpeg?lk3s=bfd515bb\u0026x-expires=1750140000\u0026x-signature=8CXKHYCOFRnNCubQGyj9l%2BnssQ8%3D\u0026from=3218412987","https://p11-sign.douyinpic.com/tos-cn-p-0015/oANJBvzVAi9CIWztIC0giBnPELefANSQtADITE~noop.jpeg?lk3s=bfd515bb\u0026x-expires=1750140000\u0026x-signature=vh4L893pxVuH%2Bi1dPNzXoK8ez6M%3D\u0026from=3218412987"]},"word_sub_board":null,"word_type":1},{"article_detail_count":0,"aweme_infos":null,"can_extend_detail":false,"discuss_video_count":1,"display_style":0,"drift_info":null,"event_time":1750066789,"group_id":"7514896191449634082","hot_value":8888744,"hotlist_param":"{\"version\":1}","label":0,"position":15,"related_words":null,"sentence_id":"2133441","sentence_tag":4003,"video_count":2,"view_count":41393724,"word":"多方回应农户土豆遭哄抢","word_cover":{"uri":"tos-cn-p-0015/oMnPAQGSEc0eAFiB6EEIEAB4tawnCgDfBICf7m","url_list":["https://p3-sign.douyinpic.com/tos-cn-p-0015/oMnPAQGSEc0eAFiB6EEIEAB4tawnCgDfBICf7m~noop.jpeg?lk3s=bfd515bb\u0026x-expires=1750140000\u0026x-signature=5vtpP%2F%2FcYGTuxLar2CD%2FhsQchfg%3D\u0026from=3218412987","https://p9-sign.douyinpic.com/tos-cn-p-0015/oMnPAQGSEc0eAFiB6EEIEAB4tawnCgDfBICf7m~noop.jpeg?lk3s=bfd515bb\u0026x-expires=1750140000\u0026x-signature=VGtGLfdtFesautHRSQ%2F%2BS3Y%2FI3k%3D\u0026from=3218412987","https://p26-sign.douyinpic.com/tos-cn-p-0015/oMnPAQGSEc0eAFiB6EEIEAB4tawnCgDfBICf7m~noop.jpeg?lk3s=bfd515bb\u0026x-expires=1750140000\u0026x-signature=4yTkEJW0Vi2G9sESuHeAkLwx5Nc%3D\u0026from=3218412987"]},"word_sub_board":null,"word_type":1},{"article_detail_count":0,"aweme_infos":null,"can_extend_detail":false,"discuss_video_count":1,"display_style":0,"drift_info":null,"event_time":1750059597,"group_id":"7514482602888140086","hot_value":8878625,"hotlist_param":"{\"version\":1}","label":0,"position":16,"related_words":null,"sentence_id":"2133229","sentence_tag":4003,"video_count":3,"view_count":43085998,"word":"印富翁不小心吞下一只蜜蜂后猝逝","word_cover":{"uri":"tos-cn-p-0015/oMg71EQAzVeThxAfMBgMdnXk4QXCzA8eQPBUKZ","url_list":["https://p3-sign.douyinpic.com/tos-cn-p-0015/oMg71EQAzVeThxAfMBgMdnXk4QXCzA8eQPBUKZ~noop.jpeg?lk3s=bfd515bb\u0026x-expires=1750140000\u0026x-signature=LFIFWMiBTWXfc3qAL9YHt6I6kzk%3D\u0026from=3218412987","https://p11-sign.douyinpic.com/tos-cn-p-0015/oMg71EQAzVeThxAfMBgMdnXk4QXCzA8eQPBUKZ~noop.jpeg?lk3s=bfd515bb\u0026x-expires=1750140000\u0026x-signature=ImI4SP%2Bm1UXUMtE5mamd8nIfo48%3D\u0026from=3218412987","https://p26-sign.douyinpic.com/tos-cn-p-0015/oMg71EQAzVeThxAfMBgMdnXk4QXCzA8eQPBUKZ~noop.jpeg?lk3s=bfd515bb\u0026x-expires=1750140000\u0026x-signature=1zstO1ucpl6UZ%2FSmdSz4nXVCBYI%3D\u0026from=3218412987"]},"word_sub_board":null,"word_type":1},{"article_detail_count":0,"aweme_infos":null,"can_extend_detail":false,"discuss_video_count":1,"display_style":0,"drift_info":null,"event_time":1750046129,"group_id":"7368637849731716352","hot_value":8868971,"hotlist_param":"{\"version\":1}","label":0,"position":17,"related_words":null,"sentence_id":"2132869","sentence_tag":20002,"video_count":3,"view_count":44070710,"word":"夏天怎么可以不去露营","word_cover":{"uri":"tos-cn-p-3edb8c/owlauDHEv0FvAomfggoOBCok8Z1fTSJUEI6BCF","url_list":["https://p26-sign.douyinpic.com/tos-cn-p-3edb8c/owlauDHEv0FvAomfggoOBCok8Z1fTSJUEI6BCF~noop.jpeg?lk3s=bfd515bb\u0026x-expires=1750140000\u0026x-signature=o9JkNdb4GKVVmda0sk4PiweEnD8%3D\u0026from=3218412987","https://p3-sign.douyinpic.com/tos-cn-p-3edb8c/owlauDHEv0FvAomfggoOBCok8Z1fTSJUEI6BCF~noop.jpeg?lk3s=bfd515bb\u0026x-expires=1750140000\u0026x-signature=65QCBkdcl7X6TABAzQlfST8sfe4%3D\u0026from=3218412987","https://p11-sign.douyinpic.com/tos-cn-p-3edb8c/owlauDHEv0FvAomfggoOBCok8Z1fTSJUEI6BCF~noop.jpeg?lk3s=bfd515bb\u0026x-expires=1750140000\u0026x-signature=tqdZLM6CotGkLlwran%2Fao%2FQQ5HA%3D\u0026from=3218412987"]},"word_sub_board":null,"word_type":1},{"article_detail_count":0,"aweme_infos":null,"can_extend_detail":false,"discuss_video_count":1,"display_style":0,"drift_info":null,"event_time":1750039509,"group_id":"7493512039173281065","hot_value":8741649,"hotlist_param":"{\"version\":1}","label":0,"position":18,"related_words":null,"sentence_id":"2132682","sentence_tag":11000,"video_count":2,"view_count":40852787,"word":"特斯拉Model Y七座版测评","word_cover":{"uri":"tos-cn-p-0015/oAGOAkfDNIik9eoAVHdhxTvhOBuAUE6NFD85Ig","url_list":["https://p26-sign.douyinpic.com/tos-cn-p-0015/oAGOAkfDNIik9eoAVHdhxTvhOBuAUE6NFD85Ig~noop.jpeg?lk3s=bfd515bb\u0026x-expires=1750140000\u0026x-signature=G5vnGDpYiNFZtc9HMXo0OJ3iOvY%3D\u0026from=3218412987","https://p3-sign.douyinpic.com/tos-cn-p-0015/oAGOAkfDNIik9eoAVHdhxTvhOBuAUE6NFD85Ig~noop.jpeg?lk3s=bfd515bb\u0026x-expires=1750140000\u0026x-signature=qK4nFKy3ClsgqIcwTuki%2Be7K2mI%3D\u0026from=3218412987","https://p11-sign.douyinpic.com/tos-cn-p-0015/oAGOAkfDNIik9eoAVHdhxTvhOBuAUE6NFD85Ig~noop.jpeg?lk3s=bfd515bb\u0026x-expires=1750140000\u0026x-signature=RicYnGh1f8aHgmNXHRHidZPDAlg%3D\u0026from=3218412987"]},"word_sub_board":null,"word_type":1},{"article_detail_count":0,"aweme_infos":null,"can_extend_detail":false,"discuss_video_count":1,"display_style":0,"drift_info":null,"event_time":1750064519,"group_id":"7515008778976040202","hot_value":8651855,"hotlist_param":"{\"version\":1}","label":0,"position":19,"related_words":null,"sentence_id":"2133388","sentence_tag":3002,"video_count":1,"view_count":36705425,"word":"伊朗绞死一名“摩萨德”间谍","word_cover":{"uri":"tos-cn-p-0015/osBrfQaBsC4cDA7BloAAJXQBXCMRKnRfh85Zea","url_list":["https://p3-sign.douyinpic.com/tos-cn-p-0015/osBrfQaBsC4cDA7BloAAJXQBXCMRKnRfh85Zea~noop.jpeg?lk3s=bfd515bb\u0026x-expires=1750140000\u0026x-signature=fPQqhlijNP7B8cRH1VmDznim1P8%3D\u0026from=3218412987","https://p26-sign.douyinpic.com/tos-cn-p-0015/osBrfQaBsC4cDA7BloAAJXQBXCMRKnRfh85Zea~noop.jpeg?lk3s=bfd515bb\u0026x-expires=1750140000\u0026x-signature=ETDVeHRPpO3QeM5hRSpjELIAQ8k%3D\u0026from=3218412987","https://p9-sign.douyinpic.com/tos-cn-p-0015/osBrfQaBsC4cDA7BloAAJXQBXCMRKnRfh85Zea~noop.jpeg?lk3s=bfd515bb\u0026x-expires=1750140000\u0026x-signature=Jgd4hVNI44LkeaRSbEW3PDdiOCY%3D\u0026from=3218412987"]},"word_sub_board":null,"word_type":1},{"article_detail_count":0,"aweme_infos":null,"can_extend_detail":false,"discuss_video_count":1,"display_style":0,"drift_info":null,"event_time":1750040384,"group_id":"7502301783828763942","hot_value":8611345,"hotlist_param":"{\"version\":1}","label":0,"position":20,"related_words":null,"sentence_id":"2132712","sentence_tag":16000,"video_count":3,"view_count":41272671,"word":"618必买穿搭好物清单","word_cover":{"uri":"tos-cn-p-0015/oYABOFztTTsQDRVN9fTBkMAwgCEvA9NIooyTEf","url_list":["https://p11-sign.douyinpic.com/tos-cn-p-0015/oYABOFztTTsQDRVN9fTBkMAwgCEvA9NIooyTEf~noop.jpeg?lk3s=bfd515bb\u0026x-expires=1750140000\u0026x-signature=etFPuJphiB2yqcX9Ae6v28DPf3E%3D\u0026from=3218412987","https://p26-sign.douyinpic.com/tos-cn-p-0015/oYABOFztTTsQDRVN9fTBkMAwgCEvA9NIooyTEf~noop.jpeg?lk3s=bfd515bb\u0026x-expires=1750140000\u0026x-signature=Wcnc2PihnpYAMyXK3d%2BW2hu3s8o%3D\u0026from=3218412987","https://p3-sign.douyinpic.com/tos-cn-p-0015/oYABOFztTTsQDRVN9fTBkMAwgCEvA9NIooyTEf~noop.jpeg?lk3s=bfd515bb\u0026x-expires=1750140000\u0026x-signature=wIRsHFEZRNr6yc4y4PQKPyktyGQ%3D\u0026from=3218412987"]},"word_sub_board":null,"word_type":1},{"article_detail_count":0,"aweme_infos":null,"can_extend_detail":false,"discuss_video_count":1,"display_style":0,"drift_info":null,"event_time":1750077060,"group_id":"7514970298387535154","hot_value":8003035,"hotlist_param":"{\"version\":1}","label":5,"position":21,"related_words":null,"sentence_id":"2133645","sentence_tag":20005,"video_count":1,"view_count":34850686,"word":"5分钟讲清楚洛杉矶骚乱","word_cover":{"uri":"tos-cn-p-0015c000-ce/o0Q9NeoAAzdQfd4gDEIJLUF6sJCCqwf2ECAC9o","url_list":["https://p3-sign.douyinpic.com/tos-cn-p-0015c000-ce/o0Q9NeoAAzdQfd4gDEIJLUF6sJCCqwf2ECAC9o~noop.jpeg?lk3s=bfd515bb\u0026x-expires=1750140000\u0026x-signature=YCp8JeU1aSTB9zjoMLMZOGNm%2Bj0%3D\u0026from=3218412987","https://p26-sign.douyinpic.com/tos-cn-p-0015c000-ce/o0Q9NeoAAzdQfd4gDEIJLUF6sJCCqwf2ECAC9o~noop.jpeg?lk3s=bfd515bb\u0026x-expires=1750140000\u0026x-signature=ul%2FBflxfDECbRePXKg4a6THKkNw%3D\u0026from=3218412987","https://p11-sign.douyinpic.com/tos-cn-p-0015c000-ce/o0Q9NeoAAzdQfd4gDEIJLUF6sJCCqwf2ECAC9o~noop.jpeg?lk3s=bfd515bb\u0026x-expires=1750140000\u0026x-signature=92eV0wCTKE8JIivVjPnHhtNEfng%3D\u0026from=3218412987"]},"word_sub_board":null,"word_type":1},{"article_detail_count":0,"aweme_infos":null,"can_extend_detail":false,"discuss_video_count":1,"display_style":0,"drift_info":null,"event_time":1750047074,"group_id":"7481951234514130210","hot_value":7918312,"hotlist_param":"{\"version\":1}","label":0,"position":22,"related_words":null,"sentence_id":"2132899","sentence_tag":2012,"video_count":3,"view_count":35931174,"word":"林依晨二胎得子","word_cover":{"uri":"tos-cn-p-0015/okfsgUL1lGaPFHafBRGAgPnn7ZQAICkByyI5eU","url_list":["https://p3-sign.douyinpic.com/tos-cn-p-0015/okfsgUL1lGaPFHafBRGAgPnn7ZQAICkByyI5eU~noop.jpeg?lk3s=bfd515bb\u0026x-expires=1750140000\u0026x-signature=Bz9n27SVVe5nnkiveD1OgQ3bQ1c%3D\u0026from=3218412987","https://p26-sign.douyinpic.com/tos-cn-p-0015/okfsgUL1lGaPFHafBRGAgPnn7ZQAICkByyI5eU~noop.jpeg?lk3s=bfd515bb\u0026x-expires=1750140000\u0026x-signature=0gerzVlr6AdUmb%2FrnjuRG%2B3ta1E%3D\u0026from=3218412987","https://p9-sign.douyinpic.com/tos-cn-p-0015/okfsgUL1lGaPFHafBRGAgPnn7ZQAICkByyI5eU~noop.jpeg?lk3s=bfd515bb\u0026x-expires=1750140000\u0026x-signature=StR%2B2DbPCz%2BBLTuG1ldOcC17w2s%3D\u0026from=3218412987"]},"word_sub_board":null,"word_type":1},{"article_detail_count":0,"aweme_infos":null,"can_extend_detail":false,"discuss_video_count":1,"display_style":0,"drift_info":null,"event_time":1750047099,"group_id":"7514617705455310080","hot_value":7797900,"hotlist_param":"{\"version\":1}","label":0,"position":23,"related_words":null,"sentence_id":"2132901","sentence_tag":20001,"video_count":4,"view_count":34841033,"word":"跟着苏超学人文地理","word_cover":{"uri":"tos-cn-p-0015c000-ce/oUeEXIonDc9IEN1AFXA1CQQDJwWeSk8Cszfl6o","url_list":["https://p3-sign.douyinpic.com/tos-cn-p-0015c000-ce/oUeEXIonDc9IEN1AFXA1CQQDJwWeSk8Cszfl6o~noop.jpeg?lk3s=bfd515bb\u0026x-expires=1750140000\u0026x-signature=LMs4hTjQPAJ%2FnfqP9p53bKdF%2BT4%3D\u0026from=3218412987","https://p9-sign.douyinpic.com/tos-cn-p-0015c000-ce/oUeEXIonDc9IEN1AFXA1CQQDJwWeSk8Cszfl6o~noop.jpeg?lk3s=bfd515bb\u0026x-expires=1750140000\u0026x-signature=haUYYIa5eMrf0iEBxHvNufV1bGc%3D\u0026from=3218412987","https://p26-sign.douyinpic.com/tos-cn-p-0015c000-ce/oUeEXIonDc9IEN1AFXA1CQQDJwWeSk8Cszfl6o~noop.jpeg?lk3s=bfd515bb\u0026x-expires=1750140000\u0026x-signature=7Jkg%2FwHKfwhps9UQtX2Ah6z8IQk%3D\u0026from=3218412987"]},"word_sub_board":null,"word_type":1},{"article_detail_count":0,"aweme_infos":null,"can_extend_detail":false,"discuss_video_count":1,"display_style":0,"drift_info":null,"event_time":1750116264,"group_id":"7515229680493810970","hot_value":7780168,"hotlist_param":"{\"version\":1}","label":1,"position":24,"related_words":null,"sentence_id":"2133821","sentence_tag":12000,"video_count":3,"view_count":32382407,"word":"WOL锁定大师赛前三","word_cover":{"uri":"tos-cn-p-0015/ocgGQoBEerbOBCI85HFBqBTAIKaagpfQmAeL74","url_list":["https://p3-sign.douyinpic.com/tos-cn-p-0015/ocgGQoBEerbOBCI85HFBqBTAIKaagpfQmAeL74~noop.jpeg?lk3s=bfd515bb\u0026x-expires=1750140000\u0026x-signature=ocrwlBDK3pJVKQQDSKOLgv6ZHCU%3D\u0026from=3218412987","https://p26-sign.douyinpic.com/tos-cn-p-0015/ocgGQoBEerbOBCI85HFBqBTAIKaagpfQmAeL74~noop.jpeg?lk3s=bfd515bb\u0026x-expires=1750140000\u0026x-signature=5%2FuaJe46JeA0uL8zvufR6OBqd3A%3D\u0026from=3218412987","https://p11-sign.douyinpic.com/tos-cn-p-0015/ocgGQoBEerbOBCI85HFBqBTAIKaagpfQmAeL74~noop.jpeg?lk3s=bfd515bb\u0026x-expires=1750140000\u0026x-signature=sJLPOLxJs2FP34xXJABYAiLfn4U%3D\u0026from=3218412987"]},"word_sub_board":null,"word_type":1},{"article_detail_count":0,"aweme_infos":null,"can_extend_detail":false,"discuss_video_count":1,"display_style":0,"drift_info":null,"event_time":1750032392,"group_id":"7514862693418210587","hot_value":7771541,"hotlist_param":"{\"version\":1}","label":0,"position":25,"related_words":null,"sentence_id":"2132552","sentence_tag":20002,"video_count":3,"view_count":31123847,"word":"我的社交电量用完了belike","word_cover":{"uri":"tos-cn-p-0015/oo7afBlmApZQfCcQoUGLIG9nIC0ezrDdYAGRBO","url_list":["https://p26-sign.douyinpic.com/tos-cn-p-0015/oo7afBlmApZQfCcQoUGLIG9nIC0ezrDdYAGRBO~noop.jpeg?lk3s=bfd515bb\u0026x-expires=1750140000\u0026x-signature=Oq9lpC6nN6c04UNLLJZ%2BhOF7jGs%3D\u0026from=3218412987","https://p3-sign.douyinpic.com/tos-cn-p-0015/oo7afBlmApZQfCcQoUGLIG9nIC0ezrDdYAGRBO~noop.jpeg?lk3s=bfd515bb\u0026x-expires=1750140000\u0026x-signature=0CaHQUTZ4MTqfVI%2FGprS%2F1EkrPM%3D\u0026from=3218412987","https://p9-sign.douyinpic.com/tos-cn-p-0015/oo7afBlmApZQfCcQoUGLIG9nIC0ezrDdYAGRBO~noop.jpeg?lk3s=bfd515bb\u0026x-expires=1750140000\u0026x-signature=%2F68vfiGZMIg2MquHoHCqCppp%2BM4%3D\u0026from=3218412987"]},"word_sub_board":null,"word_type":1},{"article_detail_count":0,"aweme_infos":null,"can_extend_detail":false,"discuss_video_count":1,"display_style":0,"drift_info":null,"event_time":1749990437,"group_id":"7514230280622707987","hot_value":7764935,"hotlist_param":"{\"version\":1}","label":3,"position":26,"related_words":null,"sentence_id":"2132307","sentence_tag":2012,"video_count":1,"view_count":31335786,"word":"心中之城解说上新了","word_cover":{"uri":"tos-cn-p-0015/oYQ7fvgcyimmeoMwCA8kXaAELnglfKZDBNnQ2B","url_list":["https://p3-sign.douyinpic.com/tos-cn-p-0015/oYQ7fvgcyimmeoMwCA8kXaAELnglfKZDBNnQ2B~noop.jpeg?lk3s=bfd515bb\u0026x-expires=1750140000\u0026x-signature=bTeocUB1MdtwrGEnmPO3h2hFGyk%3D\u0026from=3218412987","https://p26-sign.douyinpic.com/tos-cn-p-0015/oYQ7fvgcyimmeoMwCA8kXaAELnglfKZDBNnQ2B~noop.jpeg?lk3s=bfd515bb\u0026x-expires=1750140000\u0026x-signature=QtUcPhltwG6BFsQ22VQ06rooHhk%3D\u0026from=3218412987","https://p11-sign.douyinpic.com/tos-cn-p-0015/oYQ7fvgcyimmeoMwCA8kXaAELnglfKZDBNnQ2B~noop.jpeg?lk3s=bfd515bb\u0026x-expires=1750140000\u0026x-signature=%2FZnARcell4h3ZEUxPcLlI7Qedpc%3D\u0026from=3218412987"]},"word_sub_board":null,"word_type":1},{"article_detail_count":0,"aweme_infos":null,"can_extend_detail":false,"discuss_video_count":1,"display_style":0,"drift_info":null,"event_time":1750032603,"group_id":"7515431740149519635","hot_value":7748477,"hotlist_param":"{\"version\":1}","label":0,"position":27,"related_words":null,"sentence_id":"2132556","sentence_tag":20002,"video_count":1,"view_count":26694799,"word":"我的童年回忆喷喷笔","word_cover":{"uri":"tos-cn-p-0015c000-ce/oAtoCdKrEnoFm6uAawsITQ5N9z99DEC9AffQpe","url_list":["https://p26-sign.douyinpic.com/tos-cn-p-0015c000-ce/oAtoCdKrEnoFm6uAawsITQ5N9z99DEC9AffQpe~noop.jpeg?lk3s=bfd515bb\u0026x-expires=1750140000\u0026x-signature=CgiKQ33nRJDDlLlr%2FAMELxFEiM4%3D\u0026from=3218412987","https://p3-sign.douyinpic.com/tos-cn-p-0015c000-ce/oAtoCdKrEnoFm6uAawsITQ5N9z99DEC9AffQpe~noop.jpeg?lk3s=bfd515bb\u0026x-expires=1750140000\u0026x-signature=QPvFlUPyLYhlleB1SV9aWqhJEak%3D\u0026from=3218412987","https://p11-sign.douyinpic.com/tos-cn-p-0015c000-ce/oAtoCdKrEnoFm6uAawsITQ5N9z99DEC9AffQpe~noop.jpeg?lk3s=bfd515bb\u0026x-expires=1750140000\u0026x-signature=Pp7bQh5vHkO6yqdHKBHzwkDhOfk%3D\u0026from=3218412987"]},"word_sub_board":null,"word_type":1},{"article_detail_count":0,"aweme_infos":null,"can_extend_detail":false,"discuss_video_count":1,"display_style":0,"drift_info":null,"event_time":1750059125,"group_id":"7514907285135643942","hot_value":7747597,"hotlist_param":"{\"version\":1}","label":0,"position":28,"related_words":null,"sentence_id":"2133213","sentence_tag":3002,"video_count":1,"view_count":27423256,"word":"伊朗与以色列均发出警告","word_cover":{"uri":"tos-cn-p-0015/o8woQz0f2AjmC9l4gIFPTvDDPfomxR7EAABZPI","url_list":["https://p3-sign.douyinpic.com/tos-cn-p-0015/o8woQz0f2AjmC9l4gIFPTvDDPfomxR7EAABZPI~noop.jpeg?lk3s=bfd515bb\u0026x-expires=1750140000\u0026x-signature=neamj2Ks6sRT7BNgb3Q1spdt%2BIo%3D\u0026from=3218412987","https://p26-sign.douyinpic.com/tos-cn-p-0015/o8woQz0f2AjmC9l4gIFPTvDDPfomxR7EAABZPI~noop.jpeg?lk3s=bfd515bb\u0026x-expires=1750140000\u0026x-signature=WmbHw5UaTk%2BSBuVK7k2zPXiIgCM%3D\u0026from=3218412987","https://p11-sign.douyinpic.com/tos-cn-p-0015/o8woQz0f2AjmC9l4gIFPTvDDPfomxR7EAABZPI~noop.jpeg?lk3s=bfd515bb\u0026x-expires=1750140000\u0026x-signature=KYkGOlUSqTjFdmPvWEWYkHm%2Fu2c%3D\u0026from=3218412987"]},"word_sub_board":null,"word_type":1},{"article_detail_count":0,"aweme_infos":null,"can_extend_detail":false,"discuss_video_count":1,"display_style":0,"drift_info":null,"event_time":1750070955,"group_id":"7513437558920811791","hot_value":7744843,"hotlist_param":"{\"version\":1}","label":9,"position":29,"related_words":null,"sentence_id":"2133505","sentence_tag":1001,"video_count":10,"view_count":27144480,"word":"魔仙堡里有一堆古惑仔","word_cover":{"uri":"tos-cn-p-0015c000-ce/oo4oFp1SoA8eC9QKwIF7TjeDbfYH1hoEEACxOI","url_list":["https://p3-sign.douyinpic.com/tos-cn-p-0015c000-ce/oo4oFp1SoA8eC9QKwIF7TjeDbfYH1hoEEACxOI~noop.jpeg?lk3s=bfd515bb\u0026x-expires=1750140000\u0026x-signature=9RQQn1Tc7Pxwhymke4%2FOoeRH0IQ%3D\u0026from=3218412987","https://p26-sign.douyinpic.com/tos-cn-p-0015c000-ce/oo4oFp1SoA8eC9QKwIF7TjeDbfYH1hoEEACxOI~noop.jpeg?lk3s=bfd515bb\u0026x-expires=1750140000\u0026x-signature=9b9afQm1nKvLNx0xK7vgmejdrTs%3D\u0026from=3218412987","https://p9-sign.douyinpic.com/tos-cn-p-0015c000-ce/oo4oFp1SoA8eC9QKwIF7TjeDbfYH1hoEEACxOI~noop.jpeg?lk3s=bfd515bb\u0026x-expires=1750140000\u0026x-signature=QfWcYdodFPjs3i5QLSBEYLPcWvw%3D\u0026from=3218412987"]},"word_sub_board":[3],"word_type":1},{"article_detail_count":0,"aweme_infos":null,"can_extend_detail":false,"discuss_video_count":1,"display_style":0,"drift_info":null,"event_time":1750074488,"group_id":"7514946805383369994","hot_value":7741178,"hotlist_param":"{\"version\":1}","label":3,"position":30,"related_words":null,"sentence_id":"2133609","sentence_tag":4004,"video_count":2,"view_count":23469104,"word":"荔枝价格较上市初期暴跌七成","word_cover":{"uri":"tos-cn-p-0015c000-ce/ocUPELwJfAEBzZpVCBe0UJCKjiEeiAWCj8UIsz","url_list":["https://p11-sign.douyinpic.com/tos-cn-p-0015c000-ce/ocUPELwJfAEBzZpVCBe0UJCKjiEeiAWCj8UIsz~noop.jpeg?lk3s=bfd515bb\u0026x-expires=1750140000\u0026x-signature=7u3q%2FNSfimiHWdyBYIyg4%2BxnKRA%3D\u0026from=3218412987","https://p3-sign.douyinpic.com/tos-cn-p-0015c000-ce/ocUPELwJfAEBzZpVCBe0UJCKjiEeiAWCj8UIsz~noop.jpeg?lk3s=bfd515bb\u0026x-expires=1750140000\u0026x-signature=Y%2BfyAylu1%2B8xui8QcG7sO1ZSPEo%3D\u0026from=3218412987","https://p26-sign.douyinpic.com/tos-cn-p-0015c000-ce/ocUPELwJfAEBzZpVCBe0UJCKjiEeiAWCj8UIsz~noop.jpeg?lk3s=bfd515bb\u0026x-expires=1750140000\u0026x-signature=TmDOc0QWcq5u8i3EcOZ39yj80QY%3D\u0026from=3218412987"]},"word_sub_board":null,"word_type":1},{"article_detail_count":0,"aweme_infos":null,"can_extend_detail":false,"discuss_video_count":1,"display_style":0,"drift_info":null,"event_time":1750063984,"group_id":"7514709491544855842","hot_value":7739197,"hotlist_param":"{\"version\":1}","label":8,"position":31,"related_words":null,"sentence_id":"2133378","sentence_tag":2002,"video_count":1,"view_count":22839407,"word":"白鹿气球连环爆好A","word_cover":{"uri":"tos-cn-p-0015/okfOz8mDTBAFKGYQEQV8vfA0OqzgcoxFDA9PE5","url_list":["https://p26-sign.douyinpic.com/tos-cn-p-0015/okfOz8mDTBAFKGYQEQV8vfA0OqzgcoxFDA9PE5~noop.jpeg?lk3s=bfd515bb\u0026x-expires=1750140000\u0026x-signature=mbVl5pBPbx7%2BjLm189feuTQSDZU%3D\u0026from=3218412987","https://p3-sign.douyinpic.com/tos-cn-p-0015/okfOz8mDTBAFKGYQEQV8vfA0OqzgcoxFDA9PE5~noop.jpeg?lk3s=bfd515bb\u0026x-expires=1750140000\u0026x-signature=DOCyIlzAE1MT4c3cMGa82r1Ltec%3D\u0026from=3218412987","https://p9-sign.douyinpic.com/tos-cn-p-0015/okfOz8mDTBAFKGYQEQV8vfA0OqzgcoxFDA9PE5~noop.jpeg?lk3s=bfd515bb\u0026x-expires=1750140000\u0026x-signature=NygwG7Py6OrtT8UOjpZ9s3aAo4M%3D\u0026from=3218412987"]},"word_sub_board":null,"word_type":1},{"article_detail_count":0,"aweme_infos":null,"can_extend_detail":false,"discuss_video_count":1,"display_style":0,"drift_info":null,"event_time":1750085065,"group_id":"7514784725329433856","hot_value":7735918,"hotlist_param":"{\"version\":1}","label":0,"position":32,"related_words":null,"sentence_id":"2133778","sentence_tag":2005,"video_count":3,"view_count":19940669,"word":"一起品一品莫愁乡","word_cover":{"uri":"tos-cn-p-0015/oAMZkFB9CDolTeA3XgC7AVsnIfY2dyAEtRIcFE","url_list":["https://p3-sign.douyinpic.com/tos-cn-p-0015/oAMZkFB9CDolTeA3XgC7AVsnIfY2dyAEtRIcFE~noop.jpeg?lk3s=bfd515bb\u0026x-expires=1750140000\u0026x-signature=%2Fuk1kvXCuk%2F0CSw9ISmSTGhOwQQ%3D\u0026from=3218412987","https://p26-sign.douyinpic.com/tos-cn-p-0015/oAMZkFB9CDolTeA3XgC7AVsnIfY2dyAEtRIcFE~noop.jpeg?lk3s=bfd515bb\u0026x-expires=1750140000\u0026x-signature=T8%2Bc9Drna5NvFo%2FOiZuND6wPZMg%3D\u0026from=3218412987","https://p11-sign.douyinpic.com/tos-cn-p-0015/oAMZkFB9CDolTeA3XgC7AVsnIfY2dyAEtRIcFE~noop.jpeg?lk3s=bfd515bb\u0026x-expires=1750140000\u0026x-signature=hKmmlI0Hoe404Q7GyR%2Bs3id2UbU%3D\u0026from=3218412987"]},"word_sub_board":null,"word_type":1},{"article_detail_count":0,"aweme_infos":null,"can_extend_detail":false,"discuss_video_count":1,"display_style":0,"drift_info":null,"event_time":1750054793,"group_id":"7514953970868049189","hot_value":7733614,"hotlist_param":"{\"version\":1}","label":5,"position":33,"related_words":null,"sentence_id":"2133091","sentence_tag":2001,"video_count":3,"view_count":19830143,"word":"羡慕酱园弄首批观众","word_cover":{"uri":"tos-cn-p-0015/okBM8i4AfIQJhiAAoNqP1TmDaBokBegMO0ExAA","url_list":["https://p26-sign.douyinpic.com/tos-cn-p-0015/okBM8i4AfIQJhiAAoNqP1TmDaBokBegMO0ExAA~noop.jpeg?lk3s=bfd515bb\u0026x-expires=1750140000\u0026x-signature=Am%2B2y4cbeP%2BgbHfFKmvDj5F8YtQ%3D\u0026from=3218412987","https://p3-sign.douyinpic.com/tos-cn-p-0015/okBM8i4AfIQJhiAAoNqP1TmDaBokBegMO0ExAA~noop.jpeg?lk3s=bfd515bb\u0026x-expires=1750140000\u0026x-signature=Akci0JnU1jKOznwW17JQL7eTjiE%3D\u0026from=3218412987","https://p11-sign.douyinpic.com/tos-cn-p-0015/okBM8i4AfIQJhiAAoNqP1TmDaBokBegMO0ExAA~noop.jpeg?lk3s=bfd515bb\u0026x-expires=1750140000\u0026x-signature=%2BCD09TAx2Gp7MoPRyAZ9mJzYQA8%3D\u0026from=3218412987"]},"word_sub_board":null,"word_type":1},{"article_detail_count":0,"aweme_infos":null,"can_extend_detail":false,"discuss_video_count":1,"display_style":0,"drift_info":null,"event_time":1750054691,"group_id":"7514990475037021467","hot_value":7728258,"hotlist_param":"{\"version\":1}","label":3,"position":34,"related_words":null,"sentence_id":"2133088","sentence_tag":2012,"video_count":3,"view_count":21270154,"word":"范丞丞生日抖音来了","word_cover":{"uri":"tos-cn-p-0015/oA3qZrCaIEnoKokA5loAPDuBTITfDrPfgAYFt9","url_list":["https://p26-sign.douyinpic.com/tos-cn-p-0015/oA3qZrCaIEnoKokA5loAPDuBTITfDrPfgAYFt9~noop.jpeg?lk3s=bfd515bb\u0026x-expires=1750140000\u0026x-signature=%2FFoLtRcYjaJSeyzaZ1P5l%2BosAow%3D\u0026from=3218412987","https://p3-sign.douyinpic.com/tos-cn-p-0015/oA3qZrCaIEnoKokA5loAPDuBTITfDrPfgAYFt9~noop.jpeg?lk3s=bfd515bb\u0026x-expires=1750140000\u0026x-signature=OsE%2BEa%2FgfKmORCy%2FnWsKNS1sBLM%3D\u0026from=3218412987","https://p11-sign.douyinpic.com/tos-cn-p-0015/oA3qZrCaIEnoKokA5loAPDuBTITfDrPfgAYFt9~noop.jpeg?lk3s=bfd515bb\u0026x-expires=1750140000\u0026x-signature=860W60dIIq0GVvcepZdYxBZYF%2F4%3D\u0026from=3218412987"]},"word_sub_board":null,"word_type":1},{"article_detail_count":0,"aweme_infos":null,"can_extend_detail":false,"discuss_video_count":1,"display_style":0,"drift_info":null,"event_time":1750033190,"group_id":"7186947643808650533","hot_value":7725168,"hotlist_param":"{\"version\":1}","label":17,"position":35,"related_words":null,"sentence_id":"2132568","sentence_tag":1002,"video_count":2,"view_count":19372045,"word":"爱我你就抱抱我山东版","word_cover":{"uri":"tos-cn-p-0015c000-ce/okaAALEx6SB1i3REzHOZPh8qPxhIAPiM0XLR4","url_list":["https://p3-sign.douyinpic.com/tos-cn-p-0015c000-ce/okaAALEx6SB1i3REzHOZPh8qPxhIAPiM0XLR4~noop.jpeg?lk3s=bfd515bb\u0026x-expires=1750140000\u0026x-signature=n18Mc57V%2Fp6VTG8M6QPZWv11ZqY%3D\u0026from=3218412987","https://p26-sign.douyinpic.com/tos-cn-p-0015c000-ce/okaAALEx6SB1i3REzHOZPh8qPxhIAPiM0XLR4~noop.jpeg?lk3s=bfd515bb\u0026x-expires=1750140000\u0026x-signature=84Ry8yJRLKy%2F2%2BTTR3KC7k2%2FZio%3D\u0026from=3218412987","https://p11-sign.douyinpic.com/tos-cn-p-0015c000-ce/okaAALEx6SB1i3REzHOZPh8qPxhIAPiM0XLR4~noop.jpeg?lk3s=bfd515bb\u0026x-expires=1750140000\u0026x-signature=tnhgKqiitDlHjPr5UEsBhnS6PHw%3D\u0026from=3218412987"]},"word_sub_board":[3],"word_type":1},{"article_detail_count":0,"aweme_infos":null,"can_extend_detail":false,"discuss_video_count":1,"display_style":0,"drift_info":null,"event_time":1749958795,"group_id":"7246851301074015545","hot_value":7716829,"hotlist_param":"{\"version\":1}","label":0,"position":36,"related_words":null,"sentence_id":"2131760","sentence_tag":20002,"video_count":3,"view_count":17561755,"word":"夏天总要来拍一次荷花吧","word_cover":{"uri":"tos-cn-p-0015/o4GMmS17DQHKB5HBEQfA8PDhFdfQACeQiQ2b3S","url_list":["https://p3-sign.douyinpic.com/tos-cn-p-0015/o4GMmS17DQHKB5HBEQfA8PDhFdfQACeQiQ2b3S~noop.jpeg?lk3s=bfd515bb\u0026x-expires=1750140000\u0026x-signature=RGWnhCWprvxFjd9F16xmrGJ7fGY%3D\u0026from=3218412987","https://p26-sign.douyinpic.com/tos-cn-p-0015/o4GMmS17DQHKB5HBEQfA8PDhFdfQACeQiQ2b3S~noop.jpeg?lk3s=bfd515bb\u0026x-expires=1750140000\u0026x-signature=zShSvOPCUMe%2BCsCKg1riK42Fttk%3D\u0026from=3218412987","https://p11-sign.douyinpic.com/tos-cn-p-0015/o4GMmS17DQHKB5HBEQfA8PDhFdfQACeQiQ2b3S~noop.jpeg?lk3s=bfd515bb\u0026x-expires=1750140000\u0026x-signature=ZNpoytocs76VgEolYFsGUP9PTQQ%3D\u0026from=3218412987"]},"word_sub_board":null,"word_type":1},{"article_detail_count":0,"aweme_infos":null,"can_extend_detail":false,"discuss_video_count":1,"display_style":0,"drift_info":null,"event_time":1750051805,"group_id":"7516029452557014272","hot_value":7716486,"hotlist_param":"{\"version\":1}","label":3,"position":37,"related_words":null,"sentence_id":"2133023","sentence_tag":2012,"video_count":1,"view_count":14972608,"word":"那艺娜：感恩每一个人","word_cover":{"uri":"tos-cn-i-0813c000-ce/oIhNCDeTQApoJ5yDIPAbfTAEA2L844ezBAIGfI","url_list":["https://p3-sign.douyinpic.com/tos-cn-i-0813c000-ce/oIhNCDeTQApoJ5yDIPAbfTAEA2L844ezBAIGfI~noop.jpeg?lk3s=bfd515bb\u0026x-expires=1750140000\u0026x-signature=xvlix5%2B9bgea9dsugFBbJNHU2iM%3D\u0026from=3218412987","https://p26-sign.douyinpic.com/tos-cn-i-0813c000-ce/oIhNCDeTQApoJ5yDIPAbfTAEA2L844ezBAIGfI~noop.jpeg?lk3s=bfd515bb\u0026x-expires=1750140000\u0026x-signature=Di%2FQMYJ97Uv8eRWsuuoye2ZEe0A%3D\u0026from=3218412987","https://p11-sign.douyinpic.com/tos-cn-i-0813c000-ce/oIhNCDeTQApoJ5yDIPAbfTAEA2L844ezBAIGfI~noop.jpeg?lk3s=bfd515bb\u0026x-expires=1750140000\u0026x-signature=NwzIO8%2FiL4ngQF5H6rk9T2c6ZyU%3D\u0026from=3218412987"]},"word_sub_board":null,"word_type":1},{"article_detail_count":0,"aweme_infos":null,"can_extend_detail":false,"discuss_video_count":1,"display_style":0,"drift_info":null,"event_time":1750049291,"group_id":"7514214894704268583","hot_value":7713917,"hotlist_param":"{\"version\":1}","label":5,"position":38,"related_words":null,"sentence_id":"2132934","sentence_tag":2002,"video_count":2,"view_count":16196856,"word":"绽放的许开心人设太全面了","word_cover":{"uri":"tos-cn-p-0015/osB6zwife0idRNAOBuBPIui6G4VJgAxEFqVTIA","url_list":["https://p11-sign.douyinpic.com/tos-cn-p-0015/osB6zwife0idRNAOBuBPIui6G4VJgAxEFqVTIA~noop.jpeg?lk3s=bfd515bb\u0026x-expires=1750140000\u0026x-signature=JIe3J35vb1W%2BXoYWP0Qy7DzN9mE%3D\u0026from=3218412987","https://p3-sign.douyinpic.com/tos-cn-p-0015/osB6zwife0idRNAOBuBPIui6G4VJgAxEFqVTIA~noop.jpeg?lk3s=bfd515bb\u0026x-expires=1750140000\u0026x-signature=JHQ%2BDuq6HdniHNebVPz4xORn2u4%3D\u0026from=3218412987","https://p26-sign.douyinpic.com/tos-cn-p-0015/osB6zwife0idRNAOBuBPIui6G4VJgAxEFqVTIA~noop.jpeg?lk3s=bfd515bb\u0026x-expires=1750140000\u0026x-signature=1xvgECTB%2B26VPs9qUIRCCf%2BfjcU%3D\u0026from=3218412987"]},"word_sub_board":null,"word_type":1},{"article_detail_count":0,"aweme_infos":null,"can_extend_detail":false,"discuss_video_count":1,"display_style":0,"drift_info":null,"event_time":1750066467,"group_id":"7511925478002595122","hot_value":7705871,"hotlist_param":"{\"version\":1}","label":3,"position":39,"related_words":null,"sentence_id":"2133432","sentence_tag":2012,"video_count":1,"view_count":13914392,"word":"华晨宇灵魂出窍变装","word_cover":{"uri":"tos-cn-p-0015/ogGMhrKOQEoeA0WAQhxAKx88kam7CrBnfBBfw3","url_list":["https://p3-sign.douyinpic.com/tos-cn-p-0015/ogGMhrKOQEoeA0WAQhxAKx88kam7CrBnfBBfw3~noop.jpeg?lk3s=bfd515bb\u0026x-expires=1750140000\u0026x-signature=U6PxDrfuLjXPmGDFOJaXdt0ousM%3D\u0026from=3218412987","https://p9-sign.douyinpic.com/tos-cn-p-0015/ogGMhrKOQEoeA0WAQhxAKx88kam7CrBnfBBfw3~noop.jpeg?lk3s=bfd515bb\u0026x-expires=1750140000\u0026x-signature=B53f8xpisqocIe9wdL%2F5WMErorw%3D\u0026from=3218412987","https://p26-sign.douyinpic.com/tos-cn-p-0015/ogGMhrKOQEoeA0WAQhxAKx88kam7CrBnfBBfw3~noop.jpeg?lk3s=bfd515bb\u0026x-expires=1750140000\u0026x-signature=vjZGH8aBFIiBoxIdq1Nm16YsnFY%3D\u0026from=3218412987"]},"word_sub_board":null,"word_type":1},{"article_detail_count":0,"aweme_infos":null,"can_extend_detail":false,"discuss_video_count":1,"display_style":0,"drift_info":null,"event_time":1750044459,"group_id":"7513981890451510539","hot_value":7700220,"hotlist_param":"{\"version\":1}","label":9,"position":40,"related_words":null,"sentence_id":"2132819","sentence_tag":1004,"video_count":10,"view_count":12711792,"word":"李慧珍我也遇到了自己的夏乔","word_cover":{"uri":"tos-cn-i-0813/oIGEmYFACoeMR45fAAA7yr8cBjBXahQQAI8Qfs","url_list":["https://p3-sign.douyinpic.com/tos-cn-i-0813/oIGEmYFACoeMR45fAAA7yr8cBjBXahQQAI8Qfs~noop.jpeg?lk3s=bfd515bb\u0026x-expires=1750140000\u0026x-signature=ik8E%2FTtDfNLESyrvn%2FMqj8L3sYA%3D\u0026from=3218412987","https://p26-sign.douyinpic.com/tos-cn-i-0813/oIGEmYFACoeMR45fAAA7yr8cBjBXahQQAI8Qfs~noop.jpeg?lk3s=bfd515bb\u0026x-expires=1750140000\u0026x-signature=oq6Awo7%2B2NKZufn8KZMC4Wn9YiA%3D\u0026from=3218412987","https://p9-sign.douyinpic.com/tos-cn-i-0813/oIGEmYFACoeMR45fAAA7yr8cBjBXahQQAI8Qfs~noop.jpeg?lk3s=bfd515bb\u0026x-expires=1750140000\u0026x-signature=Qup%2BrSQzc1yljdCgKDeeOLd5J%2BM%3D\u0026from=3218412987"]},"word_sub_board":[3],"word_type":1},{"article_detail_count":0,"aweme_infos":null,"can_extend_detail":false,"discuss_video_count":1,"display_style":0,"drift_info":null,"event_time":1750049525,"group_id":"7515353308971914553","hot_value":7698092,"hotlist_param":"{\"version\":1}","label":0,"position":41,"related_words":null,"sentence_id":"2132939","sentence_tag":20002,"video_count":2,"view_count":11177409,"word":"当我发现我妈跟刘亦菲演过戏","word_cover":{"uri":"tos-cn-p-0015c000-ce/o0p9I4eeJADqmFB5EvwipJ5iEfRK08iCLCN7NA","url_list":["https://p11-sign.douyinpic.com/tos-cn-p-0015c000-ce/o0p9I4eeJADqmFB5EvwipJ5iEfRK08iCLCN7NA~noop.jpeg?lk3s=bfd515bb\u0026x-expires=1750140000\u0026x-signature=IUkIAfwmBN%2FJ1Rz7DmfADu%2FZgjo%3D\u0026from=3218412987","https://p3-sign.douyinpic.com/tos-cn-p-0015c000-ce/o0p9I4eeJADqmFB5EvwipJ5iEfRK08iCLCN7NA~noop.jpeg?lk3s=bfd515bb\u0026x-expires=1750140000\u0026x-signature=Q0ozL9WkrOxJtLZ3hwq6WJV%2FCnk%3D\u0026from=3218412987","https://p26-sign.douyinpic.com/tos-cn-p-0015c000-ce/o0p9I4eeJADqmFB5EvwipJ5iEfRK08iCLCN7NA~noop.jpeg?lk3s=bfd515bb\u0026x-expires=1750140000\u0026x-signature=Cy8GR9JO9Y%2BS7uXcDnN%2BG5cJTg8%3D\u0026from=3218412987"]},"word_sub_board":null,"word_type":1},{"article_detail_count":0,"aweme_infos":null,"can_extend_detail":false,"discuss_video_count":1,"display_style":0,"drift_info":null,"event_time":1750066734,"group_id":"7514753546257208610","hot_value":7697721,"hotlist_param":"{\"version\":1}","label":3,"position":42,"related_words":null,"sentence_id":"2133439","sentence_tag":3002,"video_count":1,"view_count":9928230,"word":"伊朗德黑兰民众大规模外逃","word_cover":{"uri":"tos-cn-p-0015/oI3A9PIEe0IFnwnQATDI74UFafd15UBGBDfCAJ","url_list":["https://p3-sign.douyinpic.com/tos-cn-p-0015/oI3A9PIEe0IFnwnQATDI74UFafd15UBGBDfCAJ~noop.jpeg?lk3s=bfd515bb\u0026x-expires=1750140000\u0026x-signature=j9AtvvSCFrcQlNFId3KnROdSeo0%3D\u0026from=3218412987","https://p11-sign.douyinpic.com/tos-cn-p-0015/oI3A9PIEe0IFnwnQATDI74UFafd15UBGBDfCAJ~noop.jpeg?lk3s=bfd515bb\u0026x-expires=1750140000\u0026x-signature=0x1Fzo938wNHTgcXUJBhmpPoixU%3D\u0026from=3218412987","https://p26-sign.douyinpic.com/tos-cn-p-0015/oI3A9PIEe0IFnwnQATDI74UFafd15UBGBDfCAJ~noop.jpeg?lk3s=bfd515bb\u0026x-expires=1750140000\u0026x-signature=CGQZOcT9o5wqNhO8r%2B4ra8Mxp9I%3D\u0026from=3218412987"]},"word_sub_board":null,"word_type":1},{"article_detail_count":0,"aweme_infos":null,"can_extend_detail":false,"discuss_video_count":1,"display_style":0,"drift_info":null,"event_time":1750088532,"group_id":"7516546456858744083","hot_value":7694365,"hotlist_param":"{\"version\":1}","label":0,"position":43,"related_words":null,"sentence_id":"2133805","sentence_tag":21000,"video_count":3,"view_count":12652800,"word":"以方袭击伊朗国家电视台大楼","word_cover":{"uri":"tos-cn-p-0015/o0f9IAnm2fG65SaQTFBzI6xOgCFcAoADUGDD1E","url_list":["https://p3-sign.douyinpic.com/tos-cn-p-0015/o0f9IAnm2fG65SaQTFBzI6xOgCFcAoADUGDD1E~noop.jpeg?lk3s=bfd515bb\u0026x-expires=1750140000\u0026x-signature=DhuHIZQ2GbxiRaaRXZbAnhV1%2B0o%3D\u0026from=3218412987","https://p26-sign.douyinpic.com/tos-cn-p-0015/o0f9IAnm2fG65SaQTFBzI6xOgCFcAoADUGDD1E~noop.jpeg?lk3s=bfd515bb\u0026x-expires=1750140000\u0026x-signature=9sTA4zuFC6WbNCW4xIlmMF2KW2A%3D\u0026from=3218412987","https://p11-sign.douyinpic.com/tos-cn-p-0015/o0f9IAnm2fG65SaQTFBzI6xOgCFcAoADUGDD1E~noop.jpeg?lk3s=bfd515bb\u0026x-expires=1750140000\u0026x-signature=mPcSv8RXPHJew6WHff%2BBxeHMe%2B4%3D\u0026from=3218412987"]},"word_sub_board":null,"word_type":1},{"article_detail_count":0,"aweme_infos":null,"can_extend_detail":false,"discuss_video_count":1,"display_style":0,"drift_info":null,"event_time":1750088567,"group_id":"7515154485708117257","hot_value":7686617,"hotlist_param":"{\"version\":1}","label":17,"position":44,"related_words":null,"sentence_id":"2133806","sentence_tag":2005,"video_count":3,"view_count":6070856,"word":"aespa全员概念预告","word_cover":{"uri":"tos-cn-p-0015c000-ce/owfaPjHAENCEeHwqwnDbeoQDTIIASg964FaAtu","url_list":["https://p3-sign.douyinpic.com/tos-cn-p-0015c000-ce/owfaPjHAENCEeHwqwnDbeoQDTIIASg964FaAtu~noop.jpeg?lk3s=bfd515bb\u0026x-expires=1750140000\u0026x-signature=udyZvq18kFJl4Zq6lEoMNnTJUgU%3D\u0026from=3218412987","https://p9-sign.douyinpic.com/tos-cn-p-0015c000-ce/owfaPjHAENCEeHwqwnDbeoQDTIIASg964FaAtu~noop.jpeg?lk3s=bfd515bb\u0026x-expires=1750140000\u0026x-signature=6e5j5T2H1eV7hfm8m36amprTMb0%3D\u0026from=3218412987","https://p11-sign.douyinpic.com/tos-cn-p-0015c000-ce/owfaPjHAENCEeHwqwnDbeoQDTIIASg964FaAtu~noop.jpeg?lk3s=bfd515bb\u0026x-expires=1750140000\u0026x-signature=acmRmYIGx%2FLnmpvS5Cr8EfuDN4I%3D\u0026from=3218412987"]},"word_sub_board":null,"word_type":1},{"article_detail_count":0,"aweme_infos":null,"can_extend_detail":false,"discuss_video_count":1,"display_style":0,"drift_info":null,"event_time":1750047709,"group_id":"7515795388188611898","hot_value":7686531,"hotlist_param":"{\"version\":1}","label":0,"position":45,"related_words":null,"sentence_id":"2132920","sentence_tag":20002,"video_count":3,"view_count":5424419,"word":"常州队输球最大的受害者出现了","word_cover":{"uri":"tos-cn-p-0015c000-ce/ocZIOAGF2eBqjiI09JifECwaTzvCX5EzeNB1AI","url_list":["https://p3-sign.douyinpic.com/tos-cn-p-0015c000-ce/ocZIOAGF2eBqjiI09JifECwaTzvCX5EzeNB1AI~noop.jpeg?lk3s=bfd515bb\u0026x-expires=1750140000\u0026x-signature=61BMJqx5J9Daz%2BlTw8SGV8XmllM%3D\u0026from=3218412987","https://p26-sign.douyinpic.com/tos-cn-p-0015c000-ce/ocZIOAGF2eBqjiI09JifECwaTzvCX5EzeNB1AI~noop.jpeg?lk3s=bfd515bb\u0026x-expires=1750140000\u0026x-signature=7dQIxAyvU5VMrdcEfFWjL433Cm8%3D\u0026from=3218412987","https://p11-sign.douyinpic.com/tos-cn-p-0015c000-ce/ocZIOAGF2eBqjiI09JifECwaTzvCX5EzeNB1AI~noop.jpeg?lk3s=bfd515bb\u0026x-expires=1750140000\u0026x-signature=wL%2BFuyV9M7bfdYJE9ltzEsk0wq8%3D\u0026from=3218412987"]},"word_sub_board":null,"word_type":1},{"article_detail_count":0,"aweme_infos":null,"can_extend_detail":false,"discuss_video_count":1,"display_style":0,"drift_info":null,"event_time":1750062119,"group_id":"7514670142573466880","hot_value":7675947,"hotlist_param":"{\"version\":1}","label":0,"position":46,"related_words":null,"sentence_id":"2133314","sentence_tag":3002,"video_count":1,"view_count":4123481,"word":"墨西哥一市长在办公室被枪杀","word_cover":{"uri":"tos-cn-p-0015/oIBJDIoIBbQMfBz1giPKAmDPSiyoD0AA8wXejP","url_list":["https://p3-sign.douyinpic.com/tos-cn-p-0015/oIBJDIoIBbQMfBz1giPKAmDPSiyoD0AA8wXejP~noop.jpeg?lk3s=bfd515bb\u0026x-expires=1750140000\u0026x-signature=tSUoabg5pyOAf8NZ%2Bh%2FYVvwmP0I%3D\u0026from=3218412987","https://p26-sign.douyinpic.com/tos-cn-p-0015/oIBJDIoIBbQMfBz1giPKAmDPSiyoD0AA8wXejP~noop.jpeg?lk3s=bfd515bb\u0026x-expires=1750140000\u0026x-signature=7x0JgREzmHGEd%2BhRl%2FqWdS3231E%3D\u0026from=3218412987","https://p11-sign.douyinpic.com/tos-cn-p-0015/oIBJDIoIBbQMfBz1giPKAmDPSiyoD0AA8wXejP~noop.jpeg?lk3s=bfd515bb\u0026x-expires=1750140000\u0026x-signature=HFqQx61P3wrSkaFpXpKe%2Bvv3twA%3D\u0026from=3218412987"]},"word_sub_board":null,"word_type":1},{"article_detail_count":0,"aweme_infos":null,"can_extend_detail":false,"discuss_video_count":1,"display_style":0,"drift_info":null,"event_time":1750059136,"group_id":"7504487134725723433","hot_value":7670289,"hotlist_param":"{\"version\":1}","label":0,"position":47,"related_words":null,"sentence_id":"2133214","sentence_tag":20002,"video_count":7,"view_count":1906061,"word":"夏日清爽开局指南","word_cover":{"uri":"tos-cn-p-0015c000-ce/o8CgArYnKLtfFB1GQQIGLweqQ79ig1foJ8PVy7","url_list":["https://p26-sign.douyinpic.com/tos-cn-p-0015c000-ce/o8CgArYnKLtfFB1GQQIGLweqQ79ig1foJ8PVy7~noop.jpeg?lk3s=bfd515bb\u0026x-expires=1750140000\u0026x-signature=mFv7JeyG2LRGCr%2Fk3wA0VvzFF8s%3D\u0026from=3218412987","https://p3-sign.douyinpic.com/tos-cn-p-0015c000-ce/o8CgArYnKLtfFB1GQQIGLweqQ79ig1foJ8PVy7~noop.jpeg?lk3s=bfd515bb\u0026x-expires=1750140000\u0026x-signature=KaaWhl3nNQi5uqeNIzXsWlvJzcM%3D\u0026from=3218412987","https://p9-sign.douyinpic.com/tos-cn-p-0015c000-ce/o8CgArYnKLtfFB1GQQIGLweqQ79ig1foJ8PVy7~noop.jpeg?lk3s=bfd515bb\u0026x-expires=1750140000\u0026x-signature=NBgxr4blCAps4zLioel%2B9cgkW%2F4%3D\u0026from=3218412987"]},"word_sub_board":null,"word_type":1},{"article_detail_count":0,"aweme_infos":null,"can_extend_detail":false,"discuss_video_count":1,"display_style":0,"drift_info":null,"event_time":1750079307,"group_id":"7510472480437622054","hot_value":7665953,"hotlist_param":"{\"version\":1}","label":3,"position":48,"related_words":null,"sentence_id":"2133667","sentence_tag":2005,"video_count":3,"view_count":1553269,"word":"邓紫棋巡演破100场","word_cover":{"uri":"tos-cn-p-0015/ocTAgBEtmaDw9igqpMztFmOAfeCE9oIA27IhFl","url_list":["https://p3-sign.douyinpic.com/tos-cn-p-0015/ocTAgBEtmaDw9igqpMztFmOAfeCE9oIA27IhFl~noop.jpeg?lk3s=bfd515bb\u0026x-expires=1750140000\u0026x-signature=d3iARmZQbF%2FBW7ZWbronOOSVhKE%3D\u0026from=3218412987","https://p26-sign.douyinpic.com/tos-cn-p-0015/ocTAgBEtmaDw9igqpMztFmOAfeCE9oIA27IhFl~noop.jpeg?lk3s=bfd515bb\u0026x-expires=1750140000\u0026x-signature=hcHuDPp3Kdp%2B41hSbCU74sOe7wU%3D\u0026from=3218412987","https://p11-sign.douyinpic.com/tos-cn-p-0015/ocTAgBEtmaDw9igqpMztFmOAfeCE9oIA27IhFl~noop.jpeg?lk3s=bfd515bb\u0026x-expires=1750140000\u0026x-signature=PChuiU3HkYo624lLFGRl825PbAU%3D\u0026from=3218412987"]},"word_sub_board":null,"word_type":1},{"article_detail_count":0,"aweme_infos":null,"can_extend_detail":false,"discuss_video_count":1,"display_style":0,"drift_info":null,"event_time":1750037781,"group_id":"7514275870694429993","hot_value":7662053,"hotlist_param":"{\"version\":1}","label":0,"position":49,"related_words":null,"sentence_id":"2132645","sentence_tag":20002,"video_count":3,"view_count":297932,"word":"徐州啦啦队太燃了","word_cover":{"uri":"tos-cn-p-0015/osF9DEgfEOoBVwAIIBOoTCF30TEARAfkvhA9Rb","url_list":["https://p3-sign.douyinpic.com/tos-cn-p-0015/osF9DEgfEOoBVwAIIBOoTCF30TEARAfkvhA9Rb~noop.jpeg?lk3s=bfd515bb\u0026x-expires=1750140000\u0026x-signature=QfXYBGNFYqFLh9sscm1YdT%2Bfq8g%3D\u0026from=3218412987","https://p26-sign.douyinpic.com/tos-cn-p-0015/osF9DEgfEOoBVwAIIBOoTCF30TEARAfkvhA9Rb~noop.jpeg?lk3s=bfd515bb\u0026x-expires=1750140000\u0026x-signature=BOTmu%2BfK4sRk3mYPAa0dUgwhcAk%3D\u0026from=3218412987","https://p11-sign.douyinpic.com/tos-cn-p-0015/osF9DEgfEOoBVwAIIBOoTCF30TEARAfkvhA9Rb~noop.jpeg?lk3s=bfd515bb\u0026x-expires=1750140000\u0026x-signature=I%2F6PbIDazczWJcBa3yoZzIsc%2B30%3D\u0026from=3218412987"]},"word_sub_board":null,"word_type":1}]},"extra":{"fatal_item_ids":[],"logid":"2025061708594428A3A5B8A77489A74E4F","now":1750121984000},"log_pb":{"impr_id":"2025061708594428A3A5B8A77489A74E4F"},"status_code":0}